molecule_slide_generator/__init__.py
molecule_slide_generator/data_extraction.py
molecule_slide_generator/slide_generator.py
molecule_slide_generator-0.2.0.dist-info/METADATA
molecule_slide_generator-0.2.0.dist-info/WHEEL
molecule_slide_generator-0.2.0.dist-info/license.txt
molecule_slide_generator-0.2.0.dist-info/top_level.txt
molecule_slide_generator-0.2.0.dist-info/RECORD
