Metadata-Version: 2.1
Name: molecule-slide-generator
Version: 0.2.0
Summary: Generate images of molecules and their properties for use in presentations and reports
Home-page: https://github.com/kienerj/molecule-slide-generator
Author: Joos Kiener
Author-email: joos.kiener@gmail.com
Project-URL: Bug Tracker, https://github.com/kienerj/molecule-slide-generator/issues
Classifier: Programming Language :: Python :: 3
Classifier: License :: OSI Approved :: BSD License
Classifier: Operating System :: OS Independent
Classifier: Development Status :: 4 - Beta
Requires-Python: >=3.6
License-File: license.txt
Requires-Dist: numpy
Requires-Dist: pillow
